{
  "availableActions": "Доступні дії",
  "bookmarks": "Закладки",
  "copyHTML": "Копіювати HTML",
  "custom": "Задається користувачем",
  "dark": "Темний",
  "embed": "Інтегрувати",
  "embedMap": "Вбудувати карту",
  "htmlCopied": "HTML скопійовано",
  "large": "Великий",
  "legend": "Легенда",
  "light": "Світлий",
  "mapElements": "Елементи карти",
  "mapSummary": "Короткий опис карти",
  "mapTitle": "Заголовок карти",
  "medium": "Середній",
  "mode": "Режим",
  "openInMapViewer": "Відкрити у Map Viewer",
  "size": "Розмір",
  "sizeInfo": "Розміри адаптивні та визначаються висотою і шириною вікна браузера.",
  "small": "Малий"
}
