{
  "cancel": "Annuller",
  "checkPrivileges": "Kontrollér lagindstillingerne, og bekræft, at du har de rettigheder, der er nødvendige for at foretage ændringer",
  "configureTemplates": "Konfigurér skabeloner",
  "defaultValues": "Standardværdier",
  "discard": "Slet",
  "editingAllowed": "Dine rettigheder gør det muligt for dig at redigere laget",
  "editingNotAllowed": "Du har ikke tilladelse til at redigere skabeloner for dette lag",
  "emptyStateTitle": "ø_Properties list________________å",
  "emptyStateDescription": "ø_Select a template to edit properties____________________å.",
  "formatting": "Formatering",
  "history": "Historik",
  "ok": "ø_OK_____å",
  "properties": "Egenskaber",
  "readOnly": "Skabeloner er skrivebeskyttede",
  "redo": "Annullér fortryd",
  "save": "Gem",
  "saveErrorInvalidTemplate": "Laget indeholder ugyldige ændringer",
  "saveSuccessful": "Skabelonændringerne er blevet gemt",
  "templates": "Skabeloner",
  "unableToSave": "Kan ikke gemme",
  "unableToSaveTemplates": "Kan ikke gemme dine skabelonændringer",
  "undo": "Fortryd",
  "unsavedChangesTitle": "ø_Unsaved changes________________å",
  "unsavedChangesDescription": "ø_You've made changes that will be lost if you don't save first. Are you sure you want to close and lose your changes___________________________________________________________å?"
}
